pdfwordify/__init__.py
pdfwordify/converter.py
pdfwordify/pdf2word.py
pdfwordify/pdf_extract.py
pdfwordify/save_word.py
pdfwordify/Classes/Elements.py
pdfwordify/Classes/Font.py
pdfwordify/Classes/__init__.py
pdfwordify/Tools/__init__.py
pdfwordify/Tools/config.py
pdfwordify/Tools/image_extract.py
pdfwordify/Tools/table_extract.py
pdfwordify/Tools/text_extract.py
pdfwordify-0.0.1.dist-info/METADATA
pdfwordify-0.0.1.dist-info/WHEEL
pdfwordify-0.0.1.dist-info/entry_points.txt
pdfwordify-0.0.1.dist-info/licenses/LICENSE
pdfwordify-0.0.1.dist-info/RECORD
