Metadata-Version: 2.3
Name: pdfwordify
Version: 0.0.1
Summary: Tool for extracting text and tables from PDF files and saving this data in docx format
Project-URL: Homepage, https://github.com/Lem0nCat/pdfwordify/
Author-email: Lem0nCat <lemoncat.impt@gmail.com>
License:                     GNU GENERAL PUBLIC LICENSE
License-File: LICENSE
Keywords: convert,docx,extract,pdf,table,text,word
Classifier: License :: OSI Approved :: GNU General Public License v3 (GPLv3)
Classifier: Programming Language :: Python :: 3
Requires-Python: >=3.10.0
Requires-Dist: camelot-py[cv]>=0.9.0
Requires-Dist: multipledispatch>=1.0.0
Requires-Dist: pdfminer-six>=20231228
Requires-Dist: pillow>=10.3.0
Requires-Dist: pymupdf>=1.24.2
Requires-Dist: pypdf2<3.0.0
Requires-Dist: pytesseract>=0.3.10
Requires-Dist: python-docx>=1.1.0
